{
  "executionTime": 0,
  "dereferenced": false,
  "article": {
    "id": "LEGIARTI000033024678",
    "idTexte": null,
    "type": "AUTONOME",
    "texte": "Dans le but de favoriser le développement de l'emploi sur un territoire, des personnes de droit privé peuvent créer, avec des collectivités territoriales et leurs établissements publics ou avec des établissements publics de l'Etat, des groupements d'employeurs sous l'une des formes mentionnées à l'article L. 1253-2 . Les collectivités territoriales et leurs établissements publics ne peuvent constituer plus de la moitié des membres des groupements créés en application du présent article.",
    "texteHtml": "<p>Dans le but de favoriser le développement de l'emploi sur un territoire, des personnes de droit privé peuvent créer, avec des collectivités territoriales et leurs établissements publics ou avec des établissements publics de l'Etat, des groupements d'employeurs sous l'une des formes mentionnées à l'article <a href=\"/affichCodeArticle.do?cidTexte=LEGITEXT000006072050&idArticle=LEGIARTI000006901335&dateTexte=&categorieLien=cid\" title=\"Code du travail - art. L1253-2 (V)\">L. 1253-2</a>. </p><p>Les collectivités territoriales et leurs établissements publics ne peuvent constituer plus de la moitié des membres des groupements créés en application du présent article.</p>",
    "num": "L1253-19",
    "origine": "LEGI",
    "nature": "Article",
    "versionArticle": "3.0",
    "etat": "VIGUEUR",
    "dateDebut": 1470787200000,
    "dateFin": 32472144000000,
    "dateDebutExtension": 32472144000000,
    "dateFinExtension": 32472144000000,
    "inap": null,
    "ordre": 42949,
    "context": {
      "titresTM": [
        {
          "debut": "2008-05-01",
          "fin": "2999-01-01",
          "titre": "Partie législative  ",
          "xPath": "/ARTICLE/CONTEXTE/TEXTE/TM/TITRE_TM",
          "cid": "LEGISCTA000006112874",
          "id": "LEGISCTA000006112874",
          "etat": "VIGUEUR"
        },
        {
          "debut": "2008-05-01",
          "fin": "2999-01-01",
          "titre": "Première partie : Les relations individuelles de travail",
          "xPath": "/ARTICLE/CONTEXTE/TEXTE/TM/TM/TITRE_TM",
          "cid": "LEGISCTA000006132321",
          "id": "LEGISCTA000006132321",
          "etat": "VIGUEUR"
        },
        {
          "debut": "2008-05-01",
          "fin": "2999-01-01",
          "titre": "Livre II : Le contrat de travail",
          "xPath": "/ARTICLE/CONTEXTE/TEXTE/TM/TM/TM/TITRE_TM",
          "cid": "LEGISCTA000006145393",
          "id": "LEGISCTA000006145393",
          "etat": "VIGUEUR"
        },
        {
          "debut": "2008-05-01",
          "fin": "2015-04-04",
          "titre": "TITRE V : CONTRAT DE TRAVAIL TEMPORAIRE ET AUTRES CONTRATS DE MISE À DISPOSITION",
          "xPath": "/ARTICLE/CONTEXTE/TEXTE/TM/TM/TM/TM/TITRE_TM",
          "cid": "LEGISCTA000006160712",
          "id": "LEGISCTA000006160712",
          "etat": "MODIFIE"
        },
        {
          "debut": "2015-04-04",
          "fin": "2999-01-01",
          "titre": "Titre V : Contrat de travail temporaire, autres contrats de mise à disposition et portage salarial ",
          "xPath": "/ARTICLE/CONTEXTE/TEXTE/TM/TM/TM/TM/TITRE_TM",
          "cid": "LEGISCTA000006160712",
          "id": "LEGISCTA000030442282",
          "etat": "VIGUEUR"
        },
        {
          "debut": "2008-05-01",
          "fin": "2999-01-01",
          "titre": "Chapitre III : Contrats conclus avec un groupement d'employeurs",
          "xPath": "/ARTICLE/CONTEXTE/TEXTE/TM/TM/TM/TM/TM/TITRE_TM",
          "cid": "LEGISCTA000006177875",
          "id": "LEGISCTA000006177875",
          "etat": "VIGUEUR"
        },
        {
          "debut": "2008-05-01",
          "fin": "2999-01-01",
          "titre": "Section 3 : Groupement d'employeurs composé d'adhérents de droit privé et de collectivités territoriales.",
          "xPath": "/ARTICLE/CONTEXTE/TEXTE/TM/TM/TM/TM/TM/TM/TITRE_TM",
          "cid": "LEGISCTA000006189473",
          "id": "LEGISCTA000006189473",
          "etat": "VIGUEUR"
        }
      ],
      "nombreVersionParent": 1,
      "longeurChemin": 50,
      "titreTxt": [
        {
          "debut": "1973-01-03",
          "fin": "2999-01-01",
          "titre": "Code du travail",
          "xPath": "/ARTICLE/CONTEXTE/TEXTE/TITRE_TXT",
          "cid": "LEGITEXT000006072050",
          "id": "LEGITEXT000006072050",
          "etat": "VIGUEUR"
        }
      ]
    },
    "cid": "LEGIARTI000006901354",
    "cidTexte": null,
    "sectionParentCid": "LEGISCTA000006189473",
    "sectionParentId": "LEGISCTA000006189473",
    "sectionParentTitre": "Section 3 : Groupement d'employeurs composé d'adhérents de droit privé et de collectivités territoriales.",
    "fullSectionsTitre": "Partie législative   &gt; Première partie : Les relations individuelles de travail &gt; Livre II : Le contrat de travail &gt; Titre V : Contrat de travail temporaire, autres contrats de mise à disposition et portage salarial  &gt; Chapitre III : Contrats conclus avec un groupement d'employeurs &gt; Section 3 : Groupement d'employeurs composé d'adhérents de droit privé et de collectivités territoriales.",
    "refInjection": "IG-20260114",
    "idTechInjection": "LEGIARTI000033024678",
    "idEli": null,
    "idEliAlias": null,
    "calipsos": [],
    "textTitles": [
      {
        "id": "LEGITEXT000006072050",
        "titre": "Code du travail",
        "titreLong": "Code du travail",
        "etat": "VIGUEUR",
        "dateDebut": 94867200000,
        "dateFin": 32472144000000,
        "cid": "LEGITEXT000006072050",
        "datePubli": 32472144000000,
        "datePubliComputed": null,
        "dateTexte": 32472144000000,
        "dateTexteComputed": null,
        "nature": "CODE",
        "nor": "",
        "num": "",
        "numParution": "",
        "originePubli": "",
        "appliGeo": null,
        "codesNomenclatures": [],
        "visas": null,
        "nota": null,
        "notice": null,
        "travauxPreparatoires": null,
        "signataires": null,
        "dossiersLegislatifs": [],
        "ancienId": null,
        "appellations": null
      }
    ],
    "nota": "",
    "notaHtml": "<p></p><p></p><p></p><p><br clear=\"none\" /></p>",
    "activitePro": [],
    "numeroBrochure": [],
    "numeroBo": null,
    "conteneurs": [],
    "lienModifications": [
      {
        "textCid": "JORFTEXT000032983213",
        "textTitle": "LOI n°2016-1088 du 8 août 2016 - art. 90",
        "linkType": "MODIFIE",
        "linkOrientation": "cible",
        "articleNum": "90",
        "articleId": "LEGIARTI000033001170",
        "natureText": "LOI",
        "datePubliTexte": "2016-08-09",
        "dateSignaTexte": "2016-08-08",
        "dateDebutCible": "2016-08-10"
      }
    ],
    "lienCitations": [
      {
        "textCid": "LEGITEXT000006072050",
        "textTitle": "Code du travail - art. L1253-2 (V)",
        "linkType": "CITATION",
        "linkOrientation": "source",
        "articleNum": "L1253-2",
        "articleId": "LEGIARTI000006901335",
        "natureText": "CODE",
        "parentCid": null,
        "numTexte": "",
        "datePubli": 32472144000000,
        "dateDebut": 1209600000000
      }
    ],
    "lienConcordes": [
      {
        "textCid": "LEGITEXT000006072050",
        "textTitle": "Code du travail - art. L127-10 (AbD)",
        "linkType": "CONCORDE",
        "linkOrientation": "cible",
        "articleNum": "L127-10",
        "articleId": "LEGIARTI000006646325",
        "natureText": "CODE"
      },
      {
        "textCid": "LEGITEXT000006072050",
        "textTitle": "Code du travail - art. L127-10 (AbD)",
        "linkType": "CONCORDANCE",
        "linkOrientation": "source",
        "articleNum": "L127-10",
        "articleId": "LEGIARTI000006646325",
        "natureText": "CODE"
      }
    ],
    "lienAutres": [],
    "articleVersions": [
      {
        "id": "LEGIARTI000006901354",
        "etat": "MODIFIE",
        "version": "1.0",
        "dateDebut": 1209600000000,
        "dateFin": 1209600000000,
        "numero": null,
        "ordre": null
      },
      {
        "id": "LEGIARTI000018765073",
        "etat": "MODIFIE",
        "version": "2.0",
        "dateDebut": 1209600000000,
        "dateFin": 1470787200000,
        "numero": null,
        "ordre": null
      },
      {
        "id": "LEGIARTI000033024678",
        "etat": "VIGUEUR",
        "version": "3.0",
        "dateDebut": 1470787200000,
        "dateFin": 32472144000000,
        "numero": null,
        "ordre": null
      }
    ],
    "computedNums": [
      "L1253-19",
      "1253-19"
    ],
    "versionPrecedente": "LEGIARTI000018765073",
    "conditionDiffere": null,
    "historique": null,
    "surtitre": null,
    "renvoi": null,
    "infosComplementaires": null,
    "infosComplementairesHtml": null,
    "infosRestructurationBranche": null,
    "infosRestructurationBrancheHtml": null,
    "isMultipleVersions": true,
    "comporteLiensSP": false
  }
}