{
  "executionTime": 0,
  "dereferenced": false,
  "article": {
    "id": "LEGIARTI000006902821",
    "idTexte": null,
    "type": "AUTONOME",
    "texte": "Les disparités de rémunération entre les établissements d'une même entreprise ne peuvent pas, pour un même travail ou pour un travail de valeur égale, être fondées sur l'appartenance des salariés de ces établissements à l'un ou l'autre sexe.",
    "texteHtml": "<p></p>   Les disparités de rémunération entre les établissements d'une même entreprise ne peuvent pas, pour un même travail ou pour un travail de valeur égale, être fondées sur l'appartenance des salariés de ces établissements à l'un ou l'autre sexe.<p></p><p></p>",
    "num": "L3221-5",
    "origine": "LEGI",
    "nature": "Article",
    "versionArticle": "1.0",
    "etat": "VIGUEUR",
    "dateDebut": 1209600000000,
    "dateFin": 32472144000000,
    "dateDebutExtension": 32472144000000,
    "dateFinExtension": 32472144000000,
    "inap": null,
    "ordre": 214745,
    "context": {
      "titresTM": [
        {
          "debut": "2008-05-01",
          "fin": "2999-01-01",
          "titre": "Partie législative  ",
          "xPath": "/ARTICLE/CONTEXTE/TEXTE/TM/TITRE_TM",
          "cid": "LEGISCTA000006112874",
          "id": "LEGISCTA000006112874",
          "etat": "VIGUEUR"
        },
        {
          "debut": "2008-05-01",
          "fin": "2999-01-01",
          "titre": "Troisième partie : Durée du travail, salaire, intéressement, participation et épargne salariale    ",
          "xPath": "/ARTICLE/CONTEXTE/TEXTE/TM/TM/TITRE_TM",
          "cid": "LEGISCTA000006132332",
          "id": "LEGISCTA000006132332",
          "etat": "VIGUEUR"
        },
        {
          "debut": "2008-05-01",
          "fin": "2999-01-01",
          "titre": "Livre II : Salaire et avantages divers",
          "xPath": "/ARTICLE/CONTEXTE/TEXTE/TM/TM/TM/TITRE_TM",
          "cid": "LEGISCTA000006145404",
          "id": "LEGISCTA000006145404",
          "etat": "VIGUEUR"
        },
        {
          "debut": "2008-05-01",
          "fin": "2999-01-01",
          "titre": "Titre II : Egalité de rémunération entre les femmes et les hommes",
          "xPath": "/ARTICLE/CONTEXTE/TEXTE/TM/TM/TM/TM/TITRE_TM",
          "cid": "LEGISCTA000006160761",
          "id": "LEGISCTA000006160761",
          "etat": "VIGUEUR"
        },
        {
          "debut": "2008-05-01",
          "fin": "2999-01-01",
          "titre": "Chapitre Ier : Principes.",
          "xPath": "/ARTICLE/CONTEXTE/TEXTE/TM/TM/TM/TM/TM/TITRE_TM",
          "cid": "LEGISCTA000006178022",
          "id": "LEGISCTA000006178022",
          "etat": "VIGUEUR"
        }
      ],
      "nombreVersionParent": 1,
      "longeurChemin": 47,
      "titreTxt": [
        {
          "debut": "1973-01-03",
          "fin": "2999-01-01",
          "titre": "Code du travail",
          "xPath": "/ARTICLE/CONTEXTE/TEXTE/TITRE_TXT",
          "cid": "LEGITEXT000006072050",
          "id": "LEGITEXT000006072050",
          "etat": "VIGUEUR"
        }
      ]
    },
    "cid": "LEGIARTI000006902821",
    "cidTexte": null,
    "sectionParentCid": "LEGISCTA000006178022",
    "sectionParentId": "LEGISCTA000006178022",
    "sectionParentTitre": "Chapitre Ier : Principes.",
    "fullSectionsTitre": "Partie législative   &gt; Troisième partie : Durée du travail, salaire, intéressement, participation et épargne salariale     &gt; Livre II : Salaire et avantages divers &gt; Titre II : Egalité de rémunération entre les femmes et les hommes &gt; Chapitre Ier : Principes.",
    "refInjection": "MD-20260506_193142_221_BDJQUOT",
    "idTechInjection": "index_DATA_NEXT_ARTICLE_LEGIARTI000006902821",
    "idEli": null,
    "idEliAlias": null,
    "calipsos": [],
    "textTitles": [
      {
        "id": "LEGITEXT000006072050",
        "titre": "Code du travail",
        "titreLong": "Code du travail",
        "etat": "VIGUEUR",
        "dateDebut": 94867200000,
        "dateFin": 32472144000000,
        "cid": "LEGITEXT000006072050",
        "datePubli": 32472144000000,
        "datePubliComputed": null,
        "dateTexte": 32472144000000,
        "dateTexteComputed": null,
        "nature": "CODE",
        "nor": "",
        "num": "",
        "numParution": "",
        "originePubli": "",
        "appliGeo": null,
        "codesNomenclatures": [],
        "visas": null,
        "nota": null,
        "notice": null,
        "travauxPreparatoires": null,
        "signataires": null,
        "dossiersLegislatifs": [],
        "ancienId": null,
        "appellations": null
      }
    ],
    "nota": "",
    "notaHtml": "<p></p><p></p><p></p><p><br clear=\"none\" /></p>",
    "activitePro": [],
    "numeroBrochure": [],
    "numeroBo": null,
    "conteneurs": [],
    "lienModifications": [
      {
        "textCid": "JORFTEXT000000465978",
        "textTitle": "Ordonnance 2007-329 2007-03-12 JORF 13 mars 2007",
        "linkType": "CODIFICATION",
        "linkOrientation": "source",
        "articleNum": "",
        "articleId": "JORFTEXT000000465978",
        "natureText": "ORDONNANCE",
        "datePubliTexte": "2007-03-13",
        "dateSignaTexte": "2007-03-12",
        "dateDebutCible": "2999-01-01"
      }
    ],
    "lienCitations": [
      {
        "textCid": "KALITEXT000021212933",
        "textTitle": "Mise en conformité de la convention - art. 9 (VE)",
        "linkType": "CITATION",
        "linkOrientation": "cible",
        "articleNum": "9",
        "articleId": "KALIARTI000021212964",
        "natureText": "Avenant",
        "parentCid": null,
        "numTexte": "",
        "datePubli": 1256774400000,
        "dateDebut": 1246406400000
      },
      {
        "textCid": "KALITEXT000022135515",
        "textTitle": "Ecarts de rémunération entre les femmes et les ... - art. 2 (Ab)",
        "linkType": "CITATION",
        "linkOrientation": "cible",
        "articleNum": "2",
        "articleId": "KALIARTI000022135521",
        "natureText": "Avenant",
        "parentCid": null,
        "numTexte": "17",
        "datePubli": 1272240000000,
        "dateDebut": 1258416000000
      },
      {
        "textCid": "KALITEXT000023094603",
        "textTitle": "Politique salariale pour l'année 2010 - art. 4 (VE)",
        "linkType": "CITATION",
        "linkOrientation": "cible",
        "articleNum": "4",
        "articleId": "KALIARTI000023094609",
        "natureText": "Accord",
        "parentCid": null,
        "numTexte": "",
        "datePubli": 1289952000000,
        "dateDebut": 1269907200000
      },
      {
        "textCid": "KALITEXT000024462141",
        "textTitle": "Egalité professionnelle entre les femmes et les... - art. 2 (VE)",
        "linkType": "CITATION",
        "linkOrientation": "cible",
        "articleNum": "2",
        "articleId": "KALIARTI000024462150",
        "natureText": "Accord",
        "parentCid": null,
        "numTexte": "",
        "datePubli": 1313020800000,
        "dateDebut": 1290038400000
      },
      {
        "textCid": "KALITEXT000025209512",
        "textTitle": "relatif à l'égalité professionnelle et salariale - art. 2 (VNE)",
        "linkType": "CITATION",
        "linkOrientation": "cible",
        "articleNum": "2",
        "articleId": "KALIARTI000025209516",
        "natureText": "Accord",
        "parentCid": null,
        "numTexte": "",
        "datePubli": 1327881600000,
        "dateDebut": 1309824000000
      },
      {
        "textCid": "KALITEXT000029361247",
        "textTitle": "Salaires et primes au 1er février 2014 - art. (VE)",
        "linkType": "CITATION",
        "linkOrientation": "cible",
        "articleNum": "",
        "articleId": "KALIARTI000029361260",
        "natureText": "Avenant",
        "parentCid": null,
        "numTexte": "5",
        "datePubli": 1407974400000,
        "dateDebut": 1391212800000
      },
      {
        "textCid": "KALITEXT000029433623",
        "textTitle": "Salaires minima et primes au 1er mai 2014 - art. (VE)",
        "linkType": "CITATION",
        "linkOrientation": "cible",
        "articleNum": "",
        "articleId": "KALIARTI000029433626",
        "natureText": "Avenant",
        "parentCid": null,
        "numTexte": "41",
        "datePubli": 1410220800000,
        "dateDebut": 1398902400000
      },
      {
        "textCid": "KALITEXT000035993746",
        "textTitle": "Salaires et primes au 1er juillet 2017 - art. (VE)",
        "linkType": "CITATION",
        "linkOrientation": "cible",
        "articleNum": "",
        "articleId": "KALIARTI000035993749",
        "natureText": "Avenant",
        "parentCid": null,
        "numTexte": "43",
        "datePubli": 1510185600000,
        "dateDebut": 1498867200000
      },
      {
        "textCid": "KALITEXT000039071096",
        "textTitle": "Salaires à compter du 1er janvier 2019 - art. 3 (VE)",
        "linkType": "CITATION",
        "linkOrientation": "cible",
        "articleNum": "3",
        "articleId": "KALIARTI000039071101",
        "natureText": "Avenant",
        "parentCid": null,
        "numTexte": "11",
        "datePubli": 1568073600000,
        "dateDebut": 1546300800000
      },
      {
        "textCid": "KALITEXT000042258566",
        "textTitle": "Salaires minima conventionnels au 1er avril 2020 - art. (VE)",
        "linkType": "CITATION",
        "linkOrientation": "cible",
        "articleNum": "",
        "articleId": "KALIARTI000042258579",
        "natureText": "Avenant",
        "parentCid": null,
        "numTexte": "8",
        "datePubli": 1598227200000,
        "dateDebut": 1585699200000
      },
      {
        "textCid": "KALITEXT000043104464",
        "textTitle": "Salaires minimaux au 1er janvier 2020 - art. 3 (VE)",
        "linkType": "CITATION",
        "linkOrientation": "cible",
        "articleNum": "3",
        "articleId": "KALIARTI000043104469",
        "natureText": "Avenant",
        "parentCid": null,
        "numTexte": "12",
        "datePubli": 1612742400000,
        "dateDebut": 1577836800000
      },
      {
        "textCid": "KALITEXT000045518298",
        "textTitle": "Salaires pour l'année 2022 - art. (VE)",
        "linkType": "CITATION",
        "linkOrientation": "cible",
        "articleNum": "",
        "articleId": "KALIARTI000045518313",
        "natureText": "Avenant",
        "parentCid": null,
        "numTexte": "9",
        "datePubli": 1649203200000,
        "dateDebut": 1643673600000
      },
      {
        "textCid": "KALITEXT000047348865",
        "textTitle": "Salaires minimaux conventionnels garantis – NAO... - art. 3 (VE)",
        "linkType": "CITATION",
        "linkOrientation": "cible",
        "articleNum": "3",
        "articleId": "KALIARTI000047348870",
        "natureText": "Avenant",
        "parentCid": null,
        "numTexte": "16",
        "datePubli": 1679875200000,
        "dateDebut": 1667260800000
      },
      {
        "textCid": "KALITEXT000049067768",
        "textTitle": "Salaires et minima conventionnels au 1er septem... - art. (VE)",
        "linkType": "CITATION",
        "linkOrientation": "cible",
        "articleNum": "",
        "articleId": "KALIARTI000049067781",
        "natureText": "Avenant",
        "parentCid": null,
        "numTexte": "11",
        "datePubli": 1706659200000,
        "dateDebut": 1693526400000
      },
      {
        "textCid": "KALITEXT000049508746",
        "textTitle": "Salaires minimaux au 1er janvier 2024 - art. 4 (VE)",
        "linkType": "CITATION",
        "linkOrientation": "cible",
        "articleNum": "4",
        "articleId": "KALIARTI000049508752",
        "natureText": "Avenant",
        "parentCid": null,
        "numTexte": "17",
        "datePubli": 1714953600000,
        "dateDebut": 1704067200000
      },
      {
        "textCid": "KALITEXT000052455596",
        "textTitle": "Salaires minimaux conventionnels garantis – NAO... - art. 3 (VE)",
        "linkType": "CITATION",
        "linkOrientation": "cible",
        "articleNum": "3",
        "articleId": "KALIARTI000052455601",
        "natureText": "Avenant",
        "parentCid": null,
        "numTexte": "19",
        "datePubli": 1761696000000,
        "dateDebut": 1735689600000
      },
      {
        "textCid": "KALITEXT000054034055",
        "textTitle": "Salaires minimaux conventionnels garantis – NAO... - art. 3 (VE)",
        "linkType": "CITATION",
        "linkOrientation": "cible",
        "articleNum": "3",
        "articleId": "KALIARTI000054034060",
        "natureText": "Avenant",
        "parentCid": null,
        "numTexte": "21",
        "datePubli": 1777939200000,
        "dateDebut": 1767225600000
      },
      {
        "textCid": "KALITEXT000028157267",
        "textTitle": "Convention collective nationale des entreprises... - art. 3.2 (VE)",
        "linkType": "CITATION",
        "linkOrientation": "cible",
        "articleNum": "3.2",
        "articleId": "KALIARTI000028157303",
        "natureText": "Convention collective nationale",
        "parentCid": null,
        "numTexte": "",
        "datePubli": 32472144000000,
        "dateDebut": 1372636800000
      },
      {
        "textCid": "KALITEXT000045807391",
        "textTitle": "Convention collective nationale du 12 juin 2019 - art. 2 (VE)",
        "linkType": "CITATION",
        "linkOrientation": "cible",
        "articleNum": "2",
        "articleId": "KALIARTI000045807627",
        "natureText": "Convention collective nationale",
        "parentCid": null,
        "numTexte": "",
        "datePubli": 32472144000000,
        "dateDebut": 1619827200000
      },
      {
        "textCid": "KALITEXT000005653292",
        "textTitle": "Convention collective nationale du 31 mai 1995 - art. 25 (VE)",
        "linkType": "CITATION",
        "linkOrientation": "cible",
        "articleNum": "25",
        "articleId": "KALIARTI000021245164",
        "natureText": "Convention collective nationale ",
        "parentCid": null,
        "numTexte": "",
        "datePubli": 32472144000000,
        "dateDebut": 1246406400000
      },
      {
        "textCid": "KALITEXT000033414738",
        "textTitle": "Convention collective régionale du 27 juillet 2016 - art. 2 (VE)",
        "linkType": "CITATION",
        "linkOrientation": "cible",
        "articleNum": "2",
        "articleId": "KALIARTI000033414986",
        "natureText": "Convention collective régionale",
        "parentCid": null,
        "numTexte": "",
        "datePubli": 32472144000000,
        "dateDebut": 1635552000000
      },
      {
        "textCid": "KALITEXT000022135471",
        "textTitle": "Ecarts de rémunération entre les femmes et les ... - art. 2 (VE)",
        "linkType": "CITATION",
        "linkOrientation": "cible",
        "articleNum": "2",
        "articleId": "KALIARTI000022135477",
        "natureText": "Avenant",
        "parentCid": null,
        "numTexte": "46",
        "datePubli": 32472144000000,
        "dateDebut": 1258416000000
      },
      {
        "textCid": "KALITEXT000046956293",
        "textTitle": "Salaires et aux minima conventionnels - art. (VE)",
        "linkType": "CITATION",
        "linkOrientation": "cible",
        "articleNum": "",
        "articleId": "KALIARTI000046956307",
        "natureText": "Avenant",
        "parentCid": null,
        "numTexte": "10",
        "datePubli": 32472144000000,
        "dateDebut": 1664582400000
      },
      {
        "textCid": "KALITEXT000051947672",
        "textTitle": "Salaires et minima conventionnels au 1er mars 2025 - art. (VE)",
        "linkType": "CITATION",
        "linkOrientation": "cible",
        "articleNum": "",
        "articleId": "KALIARTI000051947684",
        "natureText": "Avenant",
        "parentCid": null,
        "numTexte": "12",
        "datePubli": 32472144000000,
        "dateDebut": 1740787200000
      },
      {
        "textCid": "KALITEXT000036232102",
        "textTitle": "Salaires et primes au 1er juillet 2017 - art. (VE)",
        "linkType": "CITATION",
        "linkOrientation": "cible",
        "articleNum": "",
        "articleId": "KALIARTI000036232116",
        "natureText": "Avenant",
        "parentCid": null,
        "numTexte": "6",
        "datePubli": 32472144000000,
        "dateDebut": 1498867200000
      },
      {
        "textCid": "KALITEXT000031260663",
        "textTitle": "Salaires et primes pour 2015 - art. (VE)",
        "linkType": "CITATION",
        "linkOrientation": "cible",
        "articleNum": "",
        "articleId": "KALIARTI000031260666",
        "natureText": "Avenant",
        "parentCid": null,
        "numTexte": "42",
        "datePubli": 32472144000000,
        "dateDebut": 1438041600000
      },
      {
        "textCid": "KALITEXT000045829771",
        "textTitle": "Salaires garantis (NAO 2022) - art. 3 (VE)",
        "linkType": "CITATION",
        "linkOrientation": "cible",
        "articleNum": "3",
        "articleId": "KALIARTI000045829776",
        "natureText": "Avenant",
        "parentCid": null,
        "numTexte": "15",
        "datePubli": 32472144000000,
        "dateDebut": 1640995200000
      },
      {
        "textCid": "KALITEXT000039071019",
        "textTitle": "Salaires minima au 1er avril 2019 - art. (VE)",
        "linkType": "CITATION",
        "linkOrientation": "cible",
        "articleNum": "",
        "articleId": "KALIARTI000039071036",
        "natureText": "Avenant",
        "parentCid": null,
        "numTexte": "7",
        "datePubli": 32472144000000,
        "dateDebut": 1554076800000
      },
      {
        "textCid": "KALITEXT000045204499",
        "textTitle": "Salaires minimaux conventionnels au 1er janvier... - art. 3 (VE)",
        "linkType": "CITATION",
        "linkOrientation": "cible",
        "articleNum": "3",
        "articleId": "KALIARTI000045204504",
        "natureText": "Avenant",
        "parentCid": null,
        "numTexte": "13",
        "datePubli": 32472144000000,
        "dateDebut": 1609459200000
      },
      {
        "textCid": "KALITEXT000032826571",
        "textTitle": "relatif aux classifications, aux salaires et au... - art. 3 (VNE)",
        "linkType": "CITATION",
        "linkOrientation": "cible",
        "articleNum": "3",
        "articleId": "KALIARTI000032826581",
        "natureText": "Avenant",
        "parentCid": null,
        "numTexte": "13",
        "datePubli": 32472144000000,
        "dateDebut": 1456963200000
      },
      {
        "textCid": "KALITEXT000029324377",
        "textTitle": "à l'accord du 28 juin 2002 relatif aux classifi... - art. 3 (VNE)",
        "linkType": "CITATION",
        "linkOrientation": "cible",
        "articleNum": "3",
        "articleId": "KALIARTI000029324387",
        "natureText": "Avenant",
        "parentCid": null,
        "numTexte": "11",
        "datePubli": 32472144000000,
        "dateDebut": 1394668800000
      },
      {
        "textCid": "KALITEXT000030785835",
        "textTitle": "à l'accord du 28 juin 2002 relatif aux classifi... - art. 3 (VNE)",
        "linkType": "CITATION",
        "linkOrientation": "cible",
        "articleNum": "3",
        "articleId": "KALIARTI000030785845",
        "natureText": "Avenant",
        "parentCid": null,
        "numTexte": "12",
        "datePubli": 32472144000000,
        "dateDebut": 1426118400000
      }
    ],
    "lienConcordes": [
      {
        "textCid": "LEGITEXT000006072050",
        "textTitle": "Code du travail - art. L140-2 (AbD)",
        "linkType": "CONCORDE",
        "linkOrientation": "cible",
        "articleNum": "L140-2",
        "articleId": "LEGIARTI000006647098",
        "natureText": "CODE"
      },
      {
        "textCid": "LEGITEXT000006072050",
        "textTitle": "Code du travail L140-2 alinéa 4",
        "linkType": "CONCORDANCE",
        "linkOrientation": "source",
        "articleNum": "",
        "articleId": "LEGITEXT000006072050",
        "natureText": "CODE"
      }
    ],
    "lienAutres": [],
    "articleVersions": [
      {
        "id": "LEGIARTI000006902821",
        "etat": "VIGUEUR",
        "version": "1.0",
        "dateDebut": 1209600000000,
        "dateFin": 32472144000000,
        "numero": null,
        "ordre": null
      }
    ],
    "computedNums": [
      "L3221-5",
      "3221-5"
    ],
    "versionPrecedente": null,
    "conditionDiffere": null,
    "historique": null,
    "surtitre": null,
    "renvoi": null,
    "infosComplementaires": null,
    "infosComplementairesHtml": null,
    "infosRestructurationBranche": null,
    "infosRestructurationBrancheHtml": null,
    "isMultipleVersions": false,
    "comporteLiensSP": false
  }
}